SnapGeneFileReader
