Metadata-Version: 1.0
Name: SnapGeneFileReader
Version: 0.1.11
Summary: A Python project to read and write Snapgene *.dna into dict, json, and biopython object.
Home-page: UNKNOWN
Author: yishaluo
Author-email: yishaluo@gmail.com
License: MIT
Keywords: microplate biology parser converter report
Platform: UNKNOWN
